dbt_databricks_runner/__init__.py
dbt_databricks_runner/databricks_helpers.py
dbt_databricks_runner/dbt_helpers.py
dbt_databricks_runner-0.1.1.dist-info/METADATA
dbt_databricks_runner-0.1.1.dist-info/WHEEL
dbt_databricks_runner-0.1.1.dist-info/entry_points.txt
dbt_databricks_runner-0.1.1.dist-info/RECORD
