Metadata-Version: 2.4
Name: dbt-databricks-runner
Version: 0.1.1
Summary: Add your description here
Project-URL: Homepage, https://github.com/lpsy-smart/dbt-databricks-runner
Project-URL: Documentation, https://github.com/lpsy-smart/dbt-databricks-runner
Project-URL: Repository, https://github.com/lpsy-smart/dbt-databricks-runner
Project-URL: Issues, https://github.com/lpsy-smart/dbt-databricks-runner/issues
Project-URL: Changelog, https://github.com/lpsy-smart/dbt-databricks-runner/blob/main/CHANGELOG.md
Author-email: Lance Aven Sy <lpsy@smart.com.ph>
Requires-Python: >=3.12
Requires-Dist: click>=8.2.1
Requires-Dist: databricks-connect==16.4.0
Requires-Dist: databricks-sdk[notebook]>=0.58.0
Requires-Dist: dbt-core>=1.10.6
Requires-Dist: dbt-spark-dbx-compat==1.9.2
Requires-Dist: dotenv>=0.9.9
Requires-Dist: ipykernel>=6.29.5
Requires-Dist: pip>=25.1.1
